{
 "id": "vhnga-004",
 "num": 4,
 "title": "«Воробей» — Chim sẻ (Turgenev)",
 "vi": "«Воробей» — Chim sẻ (Turgenev)",
 "ru": "Воробей",
 "icon": "📖",
 "color": "#16a34a",
 "sectionPrefix": "vhnga-004-s",
 "group": "Иван Тургенев · Thơ văn xuôi",
 "sections": [
  {
   "id": "vhnga-004-s001",
   "type": "story",
   "num": 4,
   "title": "«Воробей» — “Chim sẻ” (I. Turgenev, 1878)",
   "blocks": [
    {
     "t": "note",
     "text": "Bài thơ văn xuôi (стихотворение в прозе) nổi tiếng của I.X. Tuốc-ghê-nhép (Иван Сергеевич Тургенев, 1818–1883). Một con chim sẻ già lao xuống che chở con trước hàm chó săn — để rồi tác giả rút ra chân lý: tình yêu mạnh hơn cái chết và nỗi sợ chết."
    },
    {
     "t": "para",
     "text": "Я возвраща́лся с охо́ты и шёл по алле́е са́да. (Tôi đi săn về, bước trên lối nhỏ rợp cây trong vườn.)"
    },
    {
     "t": "para",
     "text": "Соба́ка бежа́ла впереди́ меня́. (Con chó chạy phía trước tôi.)"
    },
    {
     "t": "para",
     "text": "Вдруг она́ уме́ньшила свои́ шаги́ и начала́ кра́сться, как бы зачу́яв перед собо́ю дичь. (Bỗng nó chậm bước lại và bắt đầu rón rén, như thể đã đánh hơi thấy con mồi ở phía trước.)"
    },
    {
     "t": "para",
     "text": "Я гляну́л вдоль алле́и и уви́дел молодо́го воробья́ с желтизно́й о́коло клю́ва и пу́хом на голове́. (Tôi nhìn dọc theo lối đi và thấy một chú chim sẻ non, mép mỏ còn vàng, trên đầu lún phún lông tơ.)"
    },
    {
     "t": "para",
     "text": "Он упа́л из гнезда́ (ве́тер си́льно кача́л берёзы алле́и) и сиде́л неподви́жно, беспо́мощно растопы́рив едва́ прораста́вшие кры́лышки. (Nó rơi khỏi tổ (gió lay mạnh những hàng bạch dương ven lối) và ngồi bất động, bất lực xòe đôi cánh non vừa mới nhú.)"
    },
    {
     "t": "para",
     "text": "Моя́ соба́ка ме́дленно приближа́лась к нему́, как вдруг, сорва́вшись с бли́зкого де́рева, ста́рый чёрногру́дый воробе́й ка́мнем упа́л перед са́мой её мо́рдой — и весь взъеро́шенный, искажённый, с отча́янным и жа́лким пи́ском пры́гнул ра́за два в направле́нии зуба́стой раскры́той па́сти. (Con chó của tôi chầm chậm tiến lại gần, thì bỗng nhiên, từ một cây gần đó lao xuống, một con chim sẻ già ức đen rơi như hòn đá ngay trước mõm chó — và toàn thân xù lông, méo mó, với những tiếng kêu tuyệt vọng đáng thương, nó nhảy đôi ba lần về phía cái mõm há rộng đầy răng.)"
    },
    {
     "t": "para",
     "text": "Он ри́нулся спаса́ть, он заслони́л собо́ю своё дети́ще… но всё его́ ма́ленькое те́ло трепета́ло от у́жаса, голосо́к одича́л и охри́п, он замира́л, он же́ртвовал собо́ю! (Nó lao tới cứu, nó lấy thân mình che chở cho đứa con… nhưng cả tấm thân bé nhỏ run lên vì khiếp sợ, giọng kêu trở nên hoảng loạn và khản đặc, nó như chết lặng, nó đang hiến dâng cả mình!)"
    },
    {
     "t": "para",
     "text": "Каки́м грома́дным чудо́вищем должна́ была́ ему́ каза́ться соба́ка! (Con chó hẳn phải hiện ra trước mắt nó như một con quái vật khổng lồ biết bao!)"
    },
    {
     "t": "para",
     "text": "И всё-таки он не мог усиде́ть на свое́й высо́кой, безопа́сной ве́тке… (Vậy mà nó vẫn không thể ngồi yên trên cành cây cao an toàn của mình…)"
    },
    {
     "t": "para",
     "text": "Си́ла, сильне́е его́ во́ли, сбро́сила его́ отту́да. (Một sức mạnh, mạnh hơn cả ý chí của nó, đã ném nó từ trên ấy xuống.)"
    },
    {
     "t": "para",
     "text": "Мой Трезо́р останови́лся, попя́тился… (Con Trezor của tôi dừng lại, lùi bước…)"
    },
    {
     "t": "para",
     "text": "Ви́дно, и он призна́л э́ту си́лу. (Hẳn là, ngay cả nó cũng đã thừa nhận sức mạnh ấy.)"
    },
    {
     "t": "para",
     "text": "Я поспеши́л отозва́ть смущённого пса — и удали́лся, благогове́я. (Tôi vội gọi con chó đang bối rối trở lại — và lặng lẽ bước đi, lòng đầy thành kính.)"
    },
    {
     "t": "para",
     "text": "Да; не сме́йтесь. (Vâng; xin đừng cười.)"
    },
    {
     "t": "para",
     "text": "Я благогове́л перед той ма́ленькой герои́ческой пти́цей, перед любо́вным её поры́вом. (Tôi đã thành kính trước chú chim bé nhỏ anh hùng ấy, trước niềm thôi thúc yêu thương của nó.)"
    },
    {
     "t": "para",
     "text": "Любо́вь, ду́мал я, сильне́е сме́рти и стра́ха сме́рти. (Tình yêu, tôi nghĩ, mạnh hơn cái chết và nỗi sợ chết.)"
    },
    {
     "t": "para",
     "text": "То́лько е́ю, то́лько любо́вью де́ржится и дви́жется жизнь. (Chỉ nhờ nó, chỉ nhờ tình yêu mà sự sống mới được giữ gìn và chuyển động.)"
    },
    {
     "t": "para",
     "text": "Апре́ль 1878 г. (Tháng Tư năm 1878.)"
    },
    {
     "t": "subhead",
     "text": "Từ khó"
    },
    {
     "t": "vocab",
     "ru": "возвраща́ться",
     "vi": "trở về",
     "g": null
    },
    {
     "t": "vocab",
     "ru": "охо́та",
     "vi": "cuộc đi săn",
     "g": null
    },
    {
     "t": "vocab",
     "ru": "алле́я",
     "vi": "lối đi rợp hàng cây",
     "g": null
    },
    {
     "t": "vocab",
     "ru": "кра́сться",
     "vi": "rón rén, lén bước",
     "g": null
    },
    {
     "t": "vocab",
     "ru": "воробе́й",
     "vi": "chim sẻ",
     "g": null
    },
    {
     "t": "vocab",
     "ru": "гнездо́",
     "vi": "tổ (chim)",
     "g": null
    },
    {
     "t": "vocab",
     "ru": "взъеро́шенный",
     "vi": "xù lông, bù xù",
     "g": null
    },
    {
     "t": "vocab",
     "ru": "писк",
     "vi": "tiếng kêu chít chít",
     "g": null
    },
    {
     "t": "vocab",
     "ru": "па́сть",
     "vi": "mõm (thú dữ), hàm há",
     "g": null
    },
    {
     "t": "vocab",
     "ru": "заслони́ть",
     "vi": "che chắn, che chở",
     "g": null
    },
    {
     "t": "vocab",
     "ru": "дети́ще",
     "vi": "đứa con, tạo vật yêu quý",
     "g": null
    },
    {
     "t": "vocab",
     "ru": "трепета́ть",
     "vi": "run rẩy",
     "g": null
    },
    {
     "t": "vocab",
     "ru": "же́ртвовать",
     "vi": "hi sinh, hiến dâng",
     "g": null
    },
    {
     "t": "vocab",
     "ru": "благогове́ть",
     "vi": "thành kính, sùng kính",
     "g": null
    },
    {
     "t": "vocab",
     "ru": "поры́в",
     "vi": "niềm thôi thúc, sự bột phát (cảm xúc)",
     "g": null
    }
   ]
  }
 ]
}
